faq/__init__.py
faq/admin.py
faq/apps.py
faq/forms.py
faq/models.py
faq/path_converters.py
faq/snippets.py
faq/tests.py
faq/urls.py
faq/views.py
faq/migrations/0001_initial.py
faq/migrations/0002_alter_answer_id_alter_answerhelpful_id_and_more.py
faq/migrations/0003_auto_20220619_0939.py
faq/migrations/0004_alter_answer_slug_alter_category_slug.py
faq/migrations/0005_rename_description_category__description.py
faq/migrations/0006_answer_is_rich_text.py
faq/migrations/__init__.py
faq/templates/faq/answer_form.html
faq/templates/faq/base.html
faq/templates/faq/categories_list.html
faq/templates/faq/category_detail.html
faq/templates/faq/comment_form.html
faq/templates/faq/comments.html
faq/templates/faq/question_base.html
faq/templates/faq/question_detail.html
faq/templates/faq/question_form.html
faq/templates/faq/questions_list.html
faq/templates/faq/vote_form.html
django_easy_faq-1.9.dist-info/LICENSE
django_easy_faq-1.9.dist-info/METADATA
django_easy_faq-1.9.dist-info/WHEEL
django_easy_faq-1.9.dist-info/top_level.txt
django_easy_faq-1.9.dist-info/RECORD
