Metadata-Version: 2.1
Name: django-easy-faq
Version: 1.9
Summary: A Django app to add great FAQ functionality to website
Home-page: https://github.com/smark-1/django-easy-faq/
Download-URL: https://pypi.python.org/pypi/django-easy-faq
License: MIT
Keywords: django,faq
Classifier: Intended Audience :: Developers
Classifier: License :: OSI Approved :: MIT License
Classifier: Operating System :: OS Independent
Classifier: Programming Language :: Python :: 3
Classifier: Programming Language :: Python :: 3.9
Classifier: Programming Language :: Python :: 3.10
Classifier: Programming Language :: Python :: 3.11
Classifier: Programming Language :: Python :: 3.12
Classifier: Framework :: Django
Requires-Python: >=3.9
License-File: LICENSE
Requires-Dist: Django >=3.2
